gllogger.py
gllogger-0.0.8.dist-info/METADATA
gllogger-0.0.8.dist-info/WHEEL
gllogger-0.0.8.dist-info/top_level.txt
gllogger-0.0.8.dist-info/RECORD
