Metadata-Version: 2.1
Name: gllogger
Version: 0.0.8
Summary: gllogger
Author-email: calm51 <calm51@protonmail.com>
Project-URL: Homepage, https://github.com/calm51/gllogger
Project-URL: Issues, https://github.com/calm51/gllogger/issues
Keywords: logger,global logger,logger hook,easy logger
Classifier: Programming Language :: Python :: 3
Requires-Python: >=3.6
Requires-Dist: better-exceptions
